dl4eo/__init__.py
dl4eo/config.py
dl4eo/pipeline.py
dl4eo/stages/__init__.py
dl4eo/stages/download_sentinel2.py
dl4eo/stages/generate_aoi.py
dl4eo/stages/generate_mask.py
dl4eo/stages/normalize_data.py
dl4eo/stages/prepare_dem.py
dl4eo/stages/prepare_sentinel1.py
dl4eo/stages/preprocess_s2.py
dl4eo-0.2.7.dist-info/METADATA
dl4eo-0.2.7.dist-info/WHEEL
dl4eo-0.2.7.dist-info/entry_points.txt
dl4eo-0.2.7.dist-info/top_level.txt
dl4eo-0.2.7.dist-info/RECORD
