Metadata-Version: 2.4
Name: dl4eo
Version: 0.2.7
Summary: Deep Learning for Earth Observation - Data Preparation Pipeline
Home-page: https://github.com/Sk-2103/dl4eo
Author: Saurabh Kaushik
Author-email: saurabh21.kaushik@gmail.com
Classifier: Programming Language :: Python :: 3
Classifier: License :: OSI Approved :: MIT License
Classifier: Operating System :: OS Independent
Classifier: Intended Audience :: Science/Research
Classifier: Topic :: Scientific/Engineering :: GIS
Requires-Python: >=3.8
Requires-Dist: numpy
Requires-Dist: rasterio
Requires-Dist: geopandas
Requires-Dist: shapely
Requires-Dist: matplotlib
Requires-Dist: joblib
Requires-Dist: pystac-client
Requires-Dist: fiona
Requires-Dist: requests
Dynamic: author
Dynamic: author-email
Dynamic: classifier
Dynamic: description
Dynamic: description-content-type
Dynamic: home-page
Dynamic: requires-dist
Dynamic: requires-python
Dynamic: summary
